chipmunk/__init__.py
chipmunk/storage_rodent.py
chipmunk-1.0.1.dist-info/DESCRIPTION.rst
chipmunk-1.0.1.dist-info/METADATA
chipmunk-1.0.1.dist-info/metadata.json
chipmunk-1.0.1.dist-info/RECORD
chipmunk-1.0.1.dist-info/top_level.txt
chipmunk-1.0.1.dist-info/WHEEL
