Metadata-Version: 2.0
Name: chipmunk
Version: 1.0.1
Summary: A very small and simple usage mechanism for Python threadlocals.
Home-page: https://github.com/Rigdon/chipmunk
Author: Rigdon
Author-email: mr.rigdon@gmail.com
License: The Unlicense
Download-URL: https://github.com/Rigdon/chipmunk/tarball/1.0
Keywords: utilities,locals,threading
Platform: UNKNOWN
Classifier: Development Status :: 5 - Production/Stable
Classifier: Intended Audience :: Developers
Classifier: License :: Public Domain
Classifier: Programming Language :: Python :: 2
Classifier: Programming Language :: Python :: 2.6
Classifier: Programming Language :: Python :: 2.7
Classifier: Programming Language :: Python :: 3
Classifier: Programming Language :: Python :: 3.2
Classifier: Programming Language :: Python :: 3.3
Classifier: Programming Language :: Python :: 3.4
